redshift_comment_mcp/__init__.py
redshift_comment_mcp/_version.py
redshift_comment_mcp/connection.py
redshift_comment_mcp/redshift_tools.py
redshift_comment_mcp/server.py
redshift_comment_mcp-0.2.0.dist-info/licenses/LICENSE
redshift_comment_mcp-0.2.0.dist-info/METADATA
redshift_comment_mcp-0.2.0.dist-info/WHEEL
redshift_comment_mcp-0.2.0.dist-info/entry_points.txt
redshift_comment_mcp-0.2.0.dist-info/top_level.txt
redshift_comment_mcp-0.2.0.dist-info/RECORD
