Metadata-Version: 2.4
Name: redshift-comment-mcp
Version: 0.2.0
Summary: A Model-Context Protocol server for Amazon Redshift.
Author-email: kouko <kouko@users.noreply.github.com>
License: MIT License
Project-URL: Homepage, https://github.com/kouko/redshift-comment-mcp
Project-URL: Bug Tracker, https://github.com/kouko/redshift-comment-mcp/issues
Classifier: Programming Language :: Python :: 3
Classifier: License :: OSI Approved :: MIT License
Classifier: Operating System :: OS Independent
Requires-Python: >=3.10
License-File: LICENSE
Requires-Dist: awswrangler[redshift]
Requires-Dist: redshift-connector
Requires-Dist: pandas
Requires-Dist: fastmcp
Provides-Extra: dev
Requires-Dist: pytest; extra == "dev"
Requires-Dist: pytest-mock; extra == "dev"
Dynamic: license-file
